{
    "community": {
        "minecraft": {
            "app_readme": "<h1>Minecraft</h1>\n<p><a href=\"https://www.minecraft.net/en-us\">Minecraft</a> is a sandbox game</p>\n<blockquote>\n<p>Application requires to run as root.</p>\n</blockquote>\n<p>Depending on the <code>Type</code> of server selected, you might need to add additional\ncustom environment variables to the application.</p>\n<p>More info can be found <a href=\"https://itzg.github.io/docker-minecraft-docs/java/server-types/bukkit-spigot/\">here</a>\nSelect the type on the sidebar.</p>\n<p>Note that some values are only applicable during the world generation.\nMore info can be found <a href=\"https://itzg.github.io/docker-minecraft-docs/\">here</a></p>",
            "categories": [
                "games"
            ],
            "description": "Minecraft is a sandbox game",
            "healthy": true,
            "healthy_error": null,
            "home": "https://www.minecraft.net/en-us",
            "location": "/__w/charts/charts/community/minecraft_mod",
            "latest_version": "1.2.14",
            "latest_app_version": "2024.6.1",
            "latest_human_version": "2024.6.1_1.2.14",
            "last_update": "2024-07-08 12:46:50",
            "name": "minecraft",
            "recommended": false,
            "title": "Minecraft",
            "maintainers": [
                {
                    "name": "truenas",
                    "url": "https://www.truenas.com/",
                    "email": "dev@ixsystems.com"
                }
            ],
            "tags": [
                "world",
                "building"
            ],
            "screenshots": [],
            "sources": [
                "https://www.minecraft.net/en-us",
                "https://github.com/truenas/charts/tree/master/community/minecraft",
                "https://github.com/itzg/docker-minecraft-server"
            ],
            "icon_url": "https://media.sys.truenas.net/apps/minecraft/icons/icon.svg"
        }
	}
}